[ {
  "name" : "TP02",
  "pkgType" : "POSTPAID",
  "pkgSubType" : "GENERAL",
  "savedOn" : "16 Apr 2026",
  "savedTime" : "13:11",
  "selectedSvcs_s2" : "[\"DATA\"]",
  "selectedSvcs_s3" : "[]",
  "selectedSvcs_s4" : "[]",
  "state" : {
    "s2" : [ {
      "id" : 1745,
      "name" : "MI MUNDO S_DA"
    } ],
    "s3" : [ ],
    "s4" : [ ],
    "price" : "299",
    "publicityCode" : "pub1",
    "endDate" : "2026-04-30",
    "isCorporate" : false
  }
}, {
  "name" : "Untitled Draft",
  "pkgType" : "PREPAID",
  "pkgSubType" : "NORMAL",
  "savedOn" : "16 Apr 2026",
  "savedTime" : "09:52",
  "selectedSvcs_s2" : "[\"VOICE\"]",
  "selectedSvcs_s3" : "[\"VOICE\"]",
  "selectedSvcs_s4" : null,
  "state" : {
    "s2" : [ {
      "id" : "1743",
      "name" : "MI MUNDO S_V"
    } ],
    "s3" : [ ],
    "s4" : [ ],
    "price" : "",
    "publicityCode" : "pub100",
    "endDate" : "",
    "isCorporate" : false
  }
} ]